vbx_tree/__init__.py
vbx_tree/main.py
vbx_tree-0.3.dist-info/METADATA
vbx_tree-0.3.dist-info/RECORD
vbx_tree-0.3.dist-info/WHEEL
vbx_tree-0.3.dist-info/top_level.txt
