Metadata-Version: 2.1
Name: vbx-tree
Version: 0.3
Summary: Fast project tree creator
Home-page: https://www.linkedin.com/in/vbxx3
Author: vbxx3
Author-email: vbabrouski@outlook.com
License: MIT
Platform: UNKNOWN
Classifier: Programming Language :: Python :: 3
Classifier: License :: OSI Approved :: MIT License
Classifier: Operating System :: OS Independent
Requires-Dist: setuptools
Requires-Dist: wheel
